uv_ci_tools/__init__.py
uv_ci_tools/__main__.py
uv_ci_tools/app/__init__.py
uv_ci_tools/app/app.py
uv_ci_tools/app/bump_version/__init__.py
uv_ci_tools/app/bump_version/app.py
uv_ci_tools/app/get/__init__.py
uv_ci_tools/app/get/app.py
uv_ci_tools/app/pre_compile/__init__.py
uv_ci_tools/app/pre_compile/app.py
uv_ci_tools/lib/__init__.py
uv_ci_tools/lib/cli.py
uv_ci_tools/lib/git.py
uv_ci_tools/lib/pyproject.py
uv_ci_tools/lib/util.py
uv_ci_tools/lib/uv.py
uv_ci_tools/lib/ver.py
uv_ci_tools/lib/ci/__init__.py
uv_ci_tools/lib/ci/base.py
uv_ci_tools/lib/ci/gitlab.py
uv_ci_tools-0.8.15.dist-info/METADATA
uv_ci_tools-0.8.15.dist-info/WHEEL
uv_ci_tools-0.8.15.dist-info/entry_points.txt
uv_ci_tools-0.8.15.dist-info/RECORD
